{"price": "$", "coordinates": {"longitude": 115.857811, "latitude": -31.9544907}, "categories": [{"alias": "italian", "title": "Italian"}], "photos": ["https://s3-media3.fl.yelpcdn.com/bphoto/TXMD6R1PUekuE70cKx4BuQ/o.jpg", "https://s3-media3.fl.yelpcdn.com/bphoto/kVNZ7P1hIYxVZrgthZhUEg/o.jpg", "https://s3-media1.fl.yelpcdn.com/bphoto/4NuSlyrMYbV5gjQGnK2F3w/o.jpg"], "image_url": "https://s3-media3.fl.yelpcdn.com/bphoto/TXMD6R1PUekuE70cKx4BuQ/o.jpg", "url": "https://www.yelp.com/biz/delisio-perth?adjust_creative=92p07_JjKyriZTQxAXRiKQ&utm_campaign=yelp_api_v3&utm_medium=api_v3_business_lookup&utm_source=92p07_JjKyriZTQxAXRiKQ", "term": "restaurants", "rating": 4.0, "review_count": 8, "id": "delisio-perth", "is_claimed": true, "location": {"city": "Perth", "address3": "", "country": "AU", "address1": "683 703 Hay St", "state": "WA", "address2": "Level 3", "zip_code": "6000"}, "hours": [{"is_open_now": false, "hours_type": "REGULAR", "open": [{"is_overnight": false, "day": 0, "start": "0900", "end": "1730"}, {"is_overnight": false, "day": 1, "start": "0900", "end": "1730"}, {"is_overnight": false, "day": 2, "start": "0900", "end": "1730"}, {"is_overnight": false, "day": 3, "start": "0900", "end": "1730"}, {"is_overnight": false, "day": 4, "start": "0900", "end": "2100"}, {"is_overnight": false, "day": 5, "start": "0900", "end": "1730"}, {"is_overnight": false, "day": 6, "start": "1100", "end": "1730"}]}], "phone": "+61894850055", "is_closed": false, "name": "Delisio"}