{"name": "Hoi Polloi Restaurant", "categories": [{"alias": "australian", "title": "Australian"}], "photos": ["https://s3-media4.fl.yelpcdn.com/bphoto/ZWhb95uMC-GX1lQWSeTCiQ/o.jpg", "https://s3-media1.fl.yelpcdn.com/bphoto/TJEgxI1n5bmcTR6ZQtITxg/o.jpg"], "coordinates": {"longitude": 149.129670895636, "latitude": -35.3027461028333}, "url": "https://www.yelp.com/biz/hoi-polloi-restaurant-parkes?adjust_creative=92p07_JjKyriZTQxAXRiKQ&utm_campaign=yelp_api_v3&utm_medium=api_v3_business_lookup&utm_source=92p07_JjKyriZTQxAXRiKQ", "term": "restaurants", "rating": 0.0, "review_count": 0, "id": "hoi-polloi-restaurant-parkes", "is_claimed": false, "location": {"city": "Parkes", "address3": "", "country": "AU", "address1": "Old Parliament House", "state": "ACT", "address2": "18 King George Terrace", "zip_code": "2600"}, "hours": [{"is_open_now": false, "open": [{"is_overnight": false, "end": "1430", "day": 0, "start": "1130"}, {"is_overnight": false, "end": "1430", "day": 1, "start": "1130"}, {"is_overnight": false, "end": "1430", "day": 2, "start": "1130"}, {"is_overnight": false, "end": "1430", "day": 3, "start": "1130"}, {"is_overnight": false, "end": "1430", "day": 4, "start": "1130"}, {"is_overnight": false, "end": "1430", "day": 5, "start": "1130"}, {"is_overnight": false, "end": "1430", "day": 6, "start": "1130"}], "hours_type": "REGULAR"}], "phone": "+611300870433", "is_closed": false, "image_url": "https://s3-media1.fl.yelpcdn.com/bphoto/ZWhb95uMC-GX1lQWSeTCiQ/o.jpg"}