{"price": "$$$", "name": "Splash Universe", "categories": [{"alias": "amusementparks", "title": "Amusement Parks"}, {"alias": "resorts", "title": "Resorts"}], "photos": ["https://s3-media2.fl.yelpcdn.com/bphoto/yxPCReTezbWDbXViXntqiw/o.jpg", "https://s3-media4.fl.yelpcdn.com/bphoto/IHaa2nbZvZSuu0vaQQ1IiA/o.jpg", "https://s3-media2.fl.yelpcdn.com/bphoto/WtpuLhBJmL7QWTy55y0QWA/o.jpg"], "coordinates": {"longitude": -83.674282, "latitude": 41.961883}, "url": "https://www.yelp.com/biz/splash-universe-dundee-2?adjust_creative=92p07_JjKyriZTQxAXRiKQ&utm_campaign=yelp_api_v3&utm_medium=api_v3_business_lookup&utm_source=92p07_JjKyriZTQxAXRiKQ", "term": "attractions", "rating": 3.0, "review_count": 36, "id": "splash-universe-dundee-2", "is_claimed": true, "location": {"city": "Dundee", "address3": "", "country": "US", "address1": "100 Whitetail Dr", "state": "MI", "address2": "", "zip_code": "48131"}, "hours": [{"is_open_now": false, "open": [{"is_overnight": false, "end": "2100", "day": 0, "start": "1000"}, {"is_overnight": false, "end": "2100", "day": 1, "start": "1000"}, {"is_overnight": false, "end": "2100", "day": 3, "start": "1000"}, {"is_overnight": false, "end": "2100", "day": 4, "start": "1000"}, {"is_overnight": false, "end": "2100", "day": 5, "start": "0900"}, {"is_overnight": false, "end": "2100", "day": 6, "start": "0900"}], "hours_type": "REGULAR"}], "phone": "+17346060149", "is_closed": false, "image_url": "https://s3-media4.fl.yelpcdn.com/bphoto/yxPCReTezbWDbXViXntqiw/o.jpg"}