{"price": "$", "name": "Oppa Korean Kitchen", "categories": [{"alias": "korean", "title": "Korean"}], "photos": ["https://s3-media3.fl.yelpcdn.com/bphoto/LfDI3198kcqaadQqOIxZiA/o.jpg", "https://s3-media4.fl.yelpcdn.com/bphoto/ZMh5pfe5RGF0oq3CLCIpZA/o.jpg", "https://s3-media2.fl.yelpcdn.com/bphoto/ibHtcLicXio7wRrmxdWF8w/o.jpg"], "coordinates": {"longitude": 144.9646149, "latitude": -37.8119011}, "url": "https://www.yelp.com/biz/oppa-korean-kitchen-melbourne?adjust_creative=92p07_JjKyriZTQxAXRiKQ&utm_campaign=yelp_api_v3&utm_medium=api_v3_business_lookup&utm_source=92p07_JjKyriZTQxAXRiKQ", "term": "restaurants", "rating": 3.5, "review_count": 15, "id": "oppa-korean-kitchen-melbourne", "is_claimed": false, "location": {"city": "Melbourne", "address3": "", "country": "AU", "address1": "271 Swanston St", "state": "VIC", "address2": "", "zip_code": "3000"}, "hours": [{"is_open_now": true, "open": [{"is_overnight": false, "end": "2200", "day": 0, "start": "1130"}, {"is_overnight": false, "end": "2200", "day": 1, "start": "1130"}, {"is_overnight": false, "end": "2200", "day": 2, "start": "1130"}, {"is_overnight": false, "end": "2300", "day": 3, "start": "1130"}, {"is_overnight": false, "end": "2300", "day": 4, "start": "1130"}, {"is_overnight": false, "end": "2300", "day": 5, "start": "1130"}, {"is_overnight": false, "end": "2200", "day": 6, "start": "1130"}], "hours_type": "REGULAR"}], "phone": "+61421351489", "is_closed": false, "image_url": "https://s3-media4.fl.yelpcdn.com/bphoto/LfDI3198kcqaadQqOIxZiA/o.jpg"}