{"price": "$$", "name": "Healthy Cow Pizza", "categories": [{"alias": "pizza", "title": "Pizza"}, {"alias": "vegetarian", "title": "Vegetarian"}, {"alias": "vegan", "title": "Vegan"}], "photos": ["https://s3-media2.fl.yelpcdn.com/bphoto/J_8W--nbcxlW5_-bGM5LuA/o.jpg", "https://s3-media3.fl.yelpcdn.com/bphoto/9Hlw8KmLBH8RRoI-bS85OA/o.jpg", "https://s3-media3.fl.yelpcdn.com/bphoto/hEhb52ALaGEEOmcZKCy_5Q/o.jpg"], "coordinates": {"longitude": -95.4581687312134, "latitude": 29.7355700869877}, "url": "https://www.yelp.com/biz/healthy-cow-pizza-houston?adjust_creative=92p07_JjKyriZTQxAXRiKQ&utm_campaign=yelp_api_v3&utm_medium=api_v3_business_lookup&utm_source=92p07_JjKyriZTQxAXRiKQ", "term": "restaurants", "rating": 4.0, "review_count": 175, "id": "healthy-cow-pizza-houston", "is_claimed": true, "location": {"city": "Houston", "address3": "", "country": "US", "address1": "3005 W Loop S Fwy", "state": "TX", "address2": "Ste 120", "zip_code": "77027"}, "hours": [{"is_open_now": true, "open": [{"day": 0, "is_overnight": false, "start": "1100", "end": "0000"}, {"day": 1, "is_overnight": false, "start": "1100", "end": "0000"}, {"day": 2, "is_overnight": false, "start": "1100", "end": "0000"}, {"day": 3, "is_overnight": false, "start": "1100", "end": "0000"}, {"day": 4, "is_overnight": true, "start": "1100", "end": "0100"}, {"day": 5, "is_overnight": true, "start": "1100", "end": "0100"}, {"day": 6, "is_overnight": false, "start": "1100", "end": "0000"}], "hours_type": "REGULAR"}], "phone": "+17135723333", "is_closed": false, "image_url": "https://s3-media3.fl.yelpcdn.com/bphoto/J_8W--nbcxlW5_-bGM5LuA/o.jpg"}