{"price": "$", "name": "Pho 290", "categories": [{"alias": "vietnamese", "title": "Vietnamese"}, {"alias": "sandwiches", "title": "Sandwiches"}], "photos": ["https://s3-media1.fl.yelpcdn.com/bphoto/FPLv9DFfc1iUcUW9oK7y1g/o.jpg", "https://s3-media3.fl.yelpcdn.com/bphoto/l1PtLHwLlkXfQvs0azlwhg/o.jpg", "https://s3-media2.fl.yelpcdn.com/bphoto/AvBJ6sdLISjBs3GWklIORA/o.jpg"], "coordinates": {"longitude": -95.4605711996555, "latitude": 29.8132923465763}, "url": "https://www.yelp.com/biz/pho-290-houston-2?adjust_creative=92p07_JjKyriZTQxAXRiKQ&utm_campaign=yelp_api_v3&utm_medium=api_v3_business_lookup&utm_source=92p07_JjKyriZTQxAXRiKQ", "term": "restaurants", "rating": 4.5, "review_count": 13, "id": "pho-290-houston-2", "is_claimed": true, "location": {"city": "Houston", "address3": "", "country": "US", "address1": "10520 Nw Fwy", "state": "TX", "address2": "", "zip_code": "77092"}, "hours": [{"is_open_now": false, "open": [{"day": 0, "is_overnight": false, "start": "1000", "end": "2000"}, {"day": 1, "is_overnight": false, "start": "1000", "end": "2000"}, {"day": 2, "is_overnight": false, "start": "1000", "end": "2000"}, {"day": 3, "is_overnight": false, "start": "1000", "end": "2000"}, {"day": 4, "is_overnight": false, "start": "1000", "end": "2000"}, {"day": 5, "is_overnight": false, "start": "1000", "end": "2000"}], "hours_type": "REGULAR"}], "phone": "+17134961944", "is_closed": false, "image_url": "https://s3-media2.fl.yelpcdn.com/bphoto/FPLv9DFfc1iUcUW9oK7y1g/o.jpg"}