{"price": "$$", "name": "Rodeway Inn Near Ybor City - Casino", "categories": [{"alias": "hotels", "title": "Hotels"}], "photos": ["https://s3-media2.fl.yelpcdn.com/bphoto/gjAtpBBTsKQfzCZEttfmbw/o.jpg", "https://s3-media1.fl.yelpcdn.com/bphoto/WgYCLqMwK3kU7KbnFF3GWA/o.jpg", "https://s3-media1.fl.yelpcdn.com/bphoto/5wORTHQgwlbS4eBihJsQpg/o.jpg"], "coordinates": {"longitude": -82.4030776466618, "latitude": 27.9697623300571}, "url": "https://www.yelp.com/biz/rodeway-inn-near-ybor-city-casino-tampa?adjust_creative=92p07_JjKyriZTQxAXRiKQ&utm_campaign=yelp_api_v3&utm_medium=api_v3_business_lookup&utm_source=92p07_JjKyriZTQxAXRiKQ", "term": "attractions", "rating": 2.5, "review_count": 6, "id": "rodeway-inn-near-ybor-city-casino-tampa", "is_claimed": true, "location": {"city": "Tampa", "address3": null, "country": "US", "address1": "2904 Melbourne Blvd", "state": "FL", "address2": null, "zip_code": "33605"}, "hours": [{"is_open_now": true, "open": [{"is_overnight": false, "end": "0000", "day": 0, "start": "0000"}, {"is_overnight": false, "end": "0000", "day": 1, "start": "0000"}, {"is_overnight": false, "end": "0000", "day": 2, "start": "0000"}, {"is_overnight": false, "end": "0000", "day": 3, "start": "0000"}, {"is_overnight": false, "end": "0000", "day": 4, "start": "0000"}, {"is_overnight": false, "end": "0000", "day": 5, "start": "0000"}, {"is_overnight": false, "end": "0000", "day": 6, "start": "0000"}], "hours_type": "REGULAR"}], "phone": "+18133742108", "is_closed": false, "image_url": "https://s3-media4.fl.yelpcdn.com/bphoto/gjAtpBBTsKQfzCZEttfmbw/o.jpg"}