{"price": "$$", "name": "Tasty Pot", "categories": [{"alias": "taiwanese", "title": "Taiwanese"}, {"alias": "bubbletea", "title": "Bubble Tea"}, {"alias": "hotpot", "title": "Hot Pot"}], "photos": ["https://s3-media2.fl.yelpcdn.com/bphoto/cjw8AQuzIKM6wwbMgLnrVQ/o.jpg", "https://s3-media2.fl.yelpcdn.com/bphoto/R6i8o9wjaRF5AWp2_3yMyQ/o.jpg", "https://s3-media2.fl.yelpcdn.com/bphoto/1RiaKA4LYkCosjudEbCFUQ/o.jpg"], "coordinates": {"longitude": -121.854393, "latitude": 37.3328018}, "url": "https://www.yelp.com/biz/tasty-pot-san-jose?adjust_creative=92p07_JjKyriZTQxAXRiKQ&utm_campaign=yelp_api_v3&utm_medium=api_v3_business_lookup&utm_source=92p07_JjKyriZTQxAXRiKQ", "term": "restaurants", "rating": 4.0, "review_count": 509, "id": "tasty-pot-san-jose", "is_claimed": true, "location": {"city": "San Jose", "address3": "", "address2": "Ste 100", "country": "US", "state": "CA", "zip_code": "95122", "address1": "1143 Story Rd"}, "hours": [{"is_open_now": true, "open": [{"is_overnight": false, "day": 0, "start": "1100", "end": "1500"}, {"is_overnight": false, "day": 0, "start": "1700", "end": "2130"}, {"is_overnight": false, "day": 1, "start": "1100", "end": "1500"}, {"is_overnight": false, "day": 1, "start": "1700", "end": "2130"}, {"is_overnight": false, "day": 2, "start": "1100", "end": "1500"}, {"is_overnight": false, "day": 2, "start": "1700", "end": "2130"}, {"is_overnight": false, "day": 3, "start": "1100", "end": "1500"}, {"is_overnight": false, "day": 3, "start": "1700", "end": "2130"}, {"is_overnight": false, "day": 4, "start": "1100", "end": "1500"}, {"is_overnight": false, "day": 4, "start": "1700", "end": "2200"}, {"is_overnight": false, "day": 5, "start": "1100", "end": "1500"}, {"is_overnight": false, "day": 5, "start": "1700", "end": "2200"}, {"is_overnight": false, "day": 6, "start": "1100", "end": "1500"}, {"is_overnight": false, "day": 6, "start": "1700", "end": "2200"}], "hours_type": "REGULAR"}], "phone": "+14082888838", "is_closed": false, "image_url": "https://s3-media4.fl.yelpcdn.com/bphoto/cjw8AQuzIKM6wwbMgLnrVQ/o.jpg"}