{"name": "Festival Of Dangerous Ideas", "categories": [{"alias": "festivals", "title": "Festivals"}], "photos": [], "coordinates": {"longitude": 151.2134552, "latitude": -33.8600807}, "term": "attractions", "rating": 4.5, "review_count": 2, "id": "festival-of-dangerous-ideas-sydney", "is_claimed": false, "location": {"city": "Sydney", "address3": "", "address2": "2 Macquarie Stree", "country": "AU", "state": "NSW", "zip_code": "2000", "address1": "Sydney Opera House"}, "url": "https://www.yelp.com/biz/festival-of-dangerous-ideas-sydney?adjust_creative=92p07_JjKyriZTQxAXRiKQ&utm_campaign=yelp_api_v3&utm_medium=api_v3_business_lookup&utm_source=92p07_JjKyriZTQxAXRiKQ", "phone": "+61292507111", "is_closed": false, "image_url": ""}