{"price": "$$", "name": "Swine", "categories": [{"alias": "newamerican", "title": "American (New)"}, {"alias": "wine_bars", "title": "Wine Bars"}, {"alias": "cocktailbars", "title": "Cocktail Bars"}], "photos": ["https://s3-media4.fl.yelpcdn.com/bphoto/3x4j10Rh35PGTk7eGJuBKQ/o.jpg", "https://s3-media4.fl.yelpcdn.com/bphoto/w8ZmQSZOXAghGPDGXldayA/o.jpg", "https://s3-media4.fl.yelpcdn.com/bphoto/a1Fn-CgSuEy1q1YB-My0TA/o.jpg"], "coordinates": {"longitude": -74.006455, "latitude": 40.734248}, "url": "https://www.yelp.com/biz/swine-new-york?adjust_creative=92p07_JjKyriZTQxAXRiKQ&utm_campaign=yelp_api_v3&utm_medium=api_v3_business_lookup&utm_source=92p07_JjKyriZTQxAXRiKQ", "term": "restaurants", "rating": 4.0, "review_count": 372, "id": "swine-new-york", "is_claimed": true, "location": {"city": "New York", "address3": "", "address2": "", "country": "US", "state": "NY", "zip_code": "10014", "address1": "531 Hudson St"}, "hours": [{"is_open_now": false, "open": [{"day": 0, "is_overnight": true, "start": "1630", "end": "0200"}, {"day": 1, "is_overnight": true, "start": "1630", "end": "0200"}, {"day": 2, "is_overnight": true, "start": "1630", "end": "0200"}, {"day": 3, "is_overnight": true, "start": "1630", "end": "0200"}, {"day": 4, "is_overnight": true, "start": "1200", "end": "0400"}, {"day": 5, "is_overnight": true, "start": "1200", "end": "0400"}, {"day": 6, "is_overnight": false, "start": "1200", "end": "0000"}], "hours_type": "REGULAR"}], "phone": "+12122557675", "is_closed": false, "image_url": "https://s3-media3.fl.yelpcdn.com/bphoto/3x4j10Rh35PGTk7eGJuBKQ/o.jpg"}