{"price": "$", "name": "Pho Binh 59 South", "categories": [{"alias": "vietnamese", "title": "Vietnamese"}, {"alias": "soup", "title": "Soup"}], "photos": ["https://s3-media2.fl.yelpcdn.com/bphoto/OkCfLYPwiDhT5TWsAj645w/o.jpg", "https://s3-media1.fl.yelpcdn.com/bphoto/7k-5H11eqGyFVx6LAYH7wA/o.jpg", "https://s3-media2.fl.yelpcdn.com/bphoto/4NgF7dtHHoqY7cHFWVko7Q/o.jpg"], "coordinates": {"longitude": -95.5313184857368, "latitude": 29.6890380980454}, "url": "https://www.yelp.com/biz/pho-binh-59-south-houston?adjust_creative=92p07_JjKyriZTQxAXRiKQ&utm_campaign=yelp_api_v3&utm_medium=api_v3_business_lookup&utm_source=92p07_JjKyriZTQxAXRiKQ", "term": "restaurants", "rating": 4.5, "review_count": 160, "id": "pho-binh-59-south-houston", "is_claimed": false, "location": {"city": "Houston", "address3": "", "country": "US", "address1": "8336 Southwest Fwy", "state": "TX", "address2": "", "zip_code": "77074"}, "hours": [{"is_open_now": false, "open": [{"day": 0, "is_overnight": false, "start": "1000", "end": "2000"}, {"day": 1, "is_overnight": false, "start": "1000", "end": "2000"}, {"day": 2, "is_overnight": false, "start": "1000", "end": "2000"}, {"day": 3, "is_overnight": false, "start": "1000", "end": "2000"}, {"day": 4, "is_overnight": false, "start": "1000", "end": "2000"}, {"day": 5, "is_overnight": false, "start": "1000", "end": "2000"}, {"day": 6, "is_overnight": false, "start": "1000", "end": "1600"}], "hours_type": "REGULAR"}], "phone": "+17137771770", "is_closed": false, "image_url": "https://s3-media1.fl.yelpcdn.com/bphoto/OkCfLYPwiDhT5TWsAj645w/o.jpg"}