{"price": "$$", "name": "Arintji", "categories": [{"alias": "tapasmallplates", "title": "Tapas/Small Plates"}, {"alias": "cafes", "title": "Cafes"}], "photos": ["https://s3-media4.fl.yelpcdn.com/bphoto/UX9eTnV0f5yKoYY21pr7Ig/o.jpg", "https://s3-media2.fl.yelpcdn.com/bphoto/BYAGlTcItNrwY_w46jpOPw/o.jpg", "https://s3-media2.fl.yelpcdn.com/bphoto/f7nHE8n-DXlBK89QjAqK-A/o.jpg"], "coordinates": {"longitude": 144.9687099, "latitude": -37.81805}, "url": "https://www.yelp.com/biz/arintji-melbourne?adjust_creative=92p07_JjKyriZTQxAXRiKQ&utm_campaign=yelp_api_v3&utm_medium=api_v3_business_lookup&utm_source=92p07_JjKyriZTQxAXRiKQ", "term": "restaurants", "rating": 3.5, "review_count": 12, "id": "arintji-melbourne", "is_claimed": false, "location": {"city": "Melbourne", "address3": null, "country": "AU", "address1": "Shop 26, Federation Square", "state": "VIC", "address2": "2 Swanston St", "zip_code": "3000"}, "hours": [{"is_open_now": true, "open": [{"is_overnight": false, "end": "2200", "day": 0, "start": "1030"}, {"is_overnight": false, "end": "2200", "day": 1, "start": "1030"}, {"is_overnight": false, "end": "2200", "day": 2, "start": "1030"}, {"is_overnight": false, "end": "2200", "day": 3, "start": "1030"}, {"is_overnight": false, "end": "2300", "day": 4, "start": "1030"}, {"is_overnight": false, "end": "2300", "day": 5, "start": "1030"}, {"is_overnight": false, "end": "2200", "day": 6, "start": "1030"}], "hours_type": "REGULAR"}], "phone": "+61396639900", "is_closed": false, "image_url": "https://s3-media4.fl.yelpcdn.com/bphoto/UX9eTnV0f5yKoYY21pr7Ig/o.jpg"}