{"price": "$", "name": "Rocking Wok Taiwanese Cuisine", "categories": [{"alias": "taiwanese", "title": "Taiwanese"}, {"alias": "hotpot", "title": "Hot Pot"}], "photos": ["https://s3-media3.fl.yelpcdn.com/bphoto/jk3x_83SkNETygqo5TejdA/o.jpg", "https://s3-media3.fl.yelpcdn.com/bphoto/-cpY849L5dJVCFVPqJ7gig/o.jpg", "https://s3-media3.fl.yelpcdn.com/bphoto/vSXaiFqmutF6F4zh3_tZIw/o.jpg"], "coordinates": {"longitude": -122.34089, "latitude": 47.65942}, "url": "https://www.yelp.com/biz/rocking-wok-taiwanese-cuisine-seattle-2?adjust_creative=92p07_JjKyriZTQxAXRiKQ&utm_campaign=yelp_api_v3&utm_medium=api_v3_business_lookup&utm_source=92p07_JjKyriZTQxAXRiKQ", "term": "restaurants", "rating": 4.0, "review_count": 249, "id": "rocking-wok-taiwanese-cuisine-seattle-2", "is_claimed": false, "location": {"city": "Seattle", "address3": "", "country": "US", "address1": "4301 Interlake Ave N", "state": "WA", "address2": "", "zip_code": "98103"}, "hours": [{"is_open_now": false, "open": [{"is_overnight": false, "end": "2130", "day": 0, "start": "1130"}, {"is_overnight": false, "end": "2130", "day": 2, "start": "1130"}, {"is_overnight": false, "end": "2130", "day": 3, "start": "1130"}, {"is_overnight": false, "end": "2130", "day": 4, "start": "1130"}, {"is_overnight": false, "end": "2130", "day": 5, "start": "1130"}, {"is_overnight": false, "end": "2130", "day": 6, "start": "1130"}], "hours_type": "REGULAR"}], "phone": "+12065454878", "is_closed": false, "image_url": "https://s3-media1.fl.yelpcdn.com/bphoto/jk3x_83SkNETygqo5TejdA/o.jpg"}