{"name": "Canberra Train Station", "categories": [{"alias": "trainstations", "title": "Train Stations"}], "photos": ["https://s3-media2.fl.yelpcdn.com/bphoto/Ihxqo8qcpbG7cACher-JVQ/o.jpg"], "coordinates": {"longitude": 149.1453706, "latitude": -35.3158464}, "term": "hotels", "rating": 0.0, "review_count": 0, "id": "canberra-train-station-canberra", "is_claimed": false, "location": {"city": "Canberra", "address3": "", "country": "AU", "address1": "Wentworth Ave", "state": "ACT", "address2": "Kingston", "zip_code": "2604"}, "url": "https://www.yelp.com/biz/canberra-train-station-canberra?adjust_creative=92p07_JjKyriZTQxAXRiKQ&utm_campaign=yelp_api_v3&utm_medium=api_v3_business_lookup&utm_source=92p07_JjKyriZTQxAXRiKQ", "phone": "+61132232", "is_closed": false, "image_url": "https://s3-media2.fl.yelpcdn.com/bphoto/Ihxqo8qcpbG7cACher-JVQ/o.jpg"}