{"price": "$$$", "name": "Punch Lane", "categories": [{"alias": "modern_european", "title": "Modern European"}, {"alias": "wine_bars", "title": "Wine Bars"}], "photos": ["https://s3-media2.fl.yelpcdn.com/bphoto/VNTVbZkc5o6lAEP1esFOkA/o.jpg", "https://s3-media3.fl.yelpcdn.com/bphoto/DUm-ElO7x9E8-MavOqHLcg/o.jpg", "https://s3-media2.fl.yelpcdn.com/bphoto/-YyeSiccdsVK1jnwyJwgGg/o.jpg"], "coordinates": {"longitude": 144.971344, "latitude": -37.8108788}, "url": "https://www.yelp.com/biz/punch-lane-melbourne?adjust_creative=92p07_JjKyriZTQxAXRiKQ&utm_campaign=yelp_api_v3&utm_medium=api_v3_business_lookup&utm_source=92p07_JjKyriZTQxAXRiKQ", "term": "restaurants", "rating": 4.5, "review_count": 17, "id": "punch-lane-melbourne", "is_claimed": true, "location": {"city": "Melbourne", "address3": null, "address2": null, "country": "AU", "state": "VIC", "zip_code": "3000", "address1": "43 Little Bourke St"}, "hours": [{"is_open_now": true, "open": [{"is_overnight": false, "day": 0, "start": "1200", "end": "0000"}, {"is_overnight": false, "day": 1, "start": "1200", "end": "0000"}, {"is_overnight": false, "day": 2, "start": "1200", "end": "0000"}, {"is_overnight": false, "day": 3, "start": "1200", "end": "0000"}, {"is_overnight": true, "day": 4, "start": "1200", "end": "0130"}, {"is_overnight": true, "day": 5, "start": "1500", "end": "0130"}, {"is_overnight": false, "day": 6, "start": "1500", "end": "0000"}], "hours_type": "REGULAR"}], "phone": "+61396394944", "is_closed": false, "image_url": "https://s3-media3.fl.yelpcdn.com/bphoto/VNTVbZkc5o6lAEP1esFOkA/o.jpg"}