{"price": "$$", "name": "Dak & Bop", "categories": [{"alias": "chicken_wings", "title": "Chicken Wings"}, {"alias": "korean", "title": "Korean"}, {"alias": "asianfusion", "title": "Asian Fusion"}], "photos": ["https://s3-media2.fl.yelpcdn.com/bphoto/6Y54uTtT7h5FyMs18KjoKQ/o.jpg", "https://s3-media2.fl.yelpcdn.com/bphoto/-hXCGLNZx-I6Ii-ogMlqAQ/o.jpg", "https://s3-media4.fl.yelpcdn.com/bphoto/MAhbbdwhRxBnL7nXSI2auA/o.jpg"], "coordinates": {"longitude": -95.382427, "latitude": 29.721726}, "url": "https://www.yelp.com/biz/dak-and-bop-houston?adjust_creative=92p07_JjKyriZTQxAXRiKQ&utm_campaign=yelp_api_v3&utm_medium=api_v3_business_lookup&utm_source=92p07_JjKyriZTQxAXRiKQ", "term": "restaurants", "rating": 3.5, "review_count": 658, "id": "dak-and-bop-houston", "is_claimed": true, "location": {"city": "Houston", "address3": "", "address2": "Ste 120", "country": "US", "state": "TX", "zip_code": "77004", "address1": "1801 Binz St"}, "hours": [{"is_open_now": false, "open": [{"is_overnight": false, "day": 0, "start": "1130", "end": "1430"}, {"is_overnight": false, "day": 0, "start": "1700", "end": "2200"}, {"is_overnight": false, "day": 1, "start": "1130", "end": "1430"}, {"is_overnight": false, "day": 1, "start": "1700", "end": "2200"}, {"is_overnight": false, "day": 2, "start": "1130", "end": "1430"}, {"is_overnight": false, "day": 2, "start": "1700", "end": "2200"}, {"is_overnight": false, "day": 3, "start": "1130", "end": "1430"}, {"is_overnight": false, "day": 3, "start": "1700", "end": "2200"}, {"is_overnight": false, "day": 4, "start": "1130", "end": "2200"}, {"is_overnight": false, "day": 5, "start": "1130", "end": "2200"}, {"is_overnight": false, "day": 6, "start": "1130", "end": "1530"}], "hours_type": "REGULAR"}], "phone": "+17135280280", "is_closed": false, "image_url": "https://s3-media2.fl.yelpcdn.com/bphoto/6Y54uTtT7h5FyMs18KjoKQ/o.jpg"}